keios_protocol_spacy/__init__.py
keios_protocol_spacy/flatbuffers/DEPSpacyResponse.py
keios_protocol_spacy/flatbuffers/NERSpacyResponse.py
keios_protocol_spacy/flatbuffers/SpacyBatchRequest.py
keios_protocol_spacy/flatbuffers/SpacyBatchResponse.py
keios_protocol_spacy/flatbuffers/SpacyMessage.py
keios_protocol_spacy/flatbuffers/SpacyMessageType.py
keios_protocol_spacy/flatbuffers/SpacyRequest.py
keios_protocol_spacy/flatbuffers/SpacyResponse.py
keios_protocol_spacy/flatbuffers/Type.py
keios_protocol_spacy-1.1.0.dist-info/WHEEL
keios_protocol_spacy-1.1.0.dist-info/METADATA
keios_protocol_spacy-1.1.0.dist-info/RECORD
